polls/__init__.py
polls/admin.py
polls/apps.py
polls/models.py
polls/tests.py
polls/urls.py
polls/views.py
polls/migrations/0001_initial.py
polls/migrations/__init__.py
polls/static/.DS_Store
polls/static/polls/.DS_Store
polls/static/polls/style.css
polls/static/polls/images/.DS_Store
polls/static/polls/images/background.png
polls/templates/polls/detail.html
polls/templates/polls/index.html
polls/templates/polls/results.html
django_polls_danilolmoura-0.1.dist-info/LICENSE
django_polls_danilolmoura-0.1.dist-info/METADATA
django_polls_danilolmoura-0.1.dist-info/WHEEL
django_polls_danilolmoura-0.1.dist-info/top_level.txt
django_polls_danilolmoura-0.1.dist-info/RECORD
